heliostrome/__init__.py
heliostrome/example.py
heliostrome/bin/__init__.py
heliostrome/bin/my_example.py
heliostrome-0.0.2.dist-info/LICENSE
heliostrome-0.0.2.dist-info/METADATA
heliostrome-0.0.2.dist-info/WHEEL
heliostrome-0.0.2.dist-info/entry_points.txt
heliostrome-0.0.2.dist-info/top_level.txt
heliostrome-0.0.2.dist-info/RECORD
